token_forge/__init__.py
token_forge/token_manager.py
TokenForge-0.5.dist-info/LICENSE
TokenForge-0.5.dist-info/METADATA
TokenForge-0.5.dist-info/WHEEL
TokenForge-0.5.dist-info/top_level.txt
TokenForge-0.5.dist-info/RECORD
