Metadata-Version: 2.1
Name: TokenForge
Version: 0.5
Summary: A package for JWT token management and authentication
Home-page: https://github.com/ridzwansyahirwan/TokenForge.git
Author: Mohammad Ridzwan Syah bin Irwan
Author-email: ridzwansyahirwan@gmail.com
License-File: LICENSE
Requires-Dist: Flask
Requires-Dist: python-dotenv
Requires-Dist: PyJWT
